LICENSE
MANIFEST.in
README
setup.py
django_onlineuser.egg-info/PKG-INFO
django_onlineuser.egg-info/SOURCES.txt
django_onlineuser.egg-info/dependency_links.txt
django_onlineuser.egg-info/not-zip-safe
django_onlineuser.egg-info/requires.txt
django_onlineuser.egg-info/top_level.txt
onlineuser/__init__.py
onlineuser/admin.py
onlineuser/middleware.py
onlineuser/models.py
onlineuser/tests.py
onlineuser/views.py
onlineuser/management/__init__.py
onlineuser/management/commands/__init__.py
onlineuser/management/commands/clean_onlineusers.py
onlineuser/management/commands/remove_all_onlineusers.py
onlineuser/migrations/0001_initial.py
onlineuser/migrations/__init__.py
onlineuser/templates/onlineuser/dummy.html
onlineuser/templates/onlineuser/onlineinfos.html
onlineuser/templatetags/__init__.py
onlineuser/templatetags/onlineuser_tags.py