Metadata-Version: 1.0
Name: django-onlineuser
Version: 0.8.7
Summary: A django app to count online users.
Home-page: https://github.com/vicalloy/onlineuser/
Author: vicalloy
Author-email: zbirder@gmail.com
License: BSD
Keywords: onlineusers,django
Platform: UNKNOWN
Classifier: Programming Language :: Python
Classifier: Topic :: Software Development :: Libraries :: Python Modules
Classifier: Framework :: Django
Classifier: Environment :: Web Environment
